{
  "fileName": "32405,,SpeedCheck 25-08-06,00001,00000,,00004,S,,920-Strom-Kalibrierung(920).csv",
  "analysisTimestamp": "2025-10-20T13:28:42.386Z",
  "detectionMethod": "automatic",
  "detectionTimestamp": "2025-10-20T13:28:42.386Z",
  "rampUp": {
    "startIndex": 427,
    "endIndex": 1229,
    "startTime": 3.423984,
    "endTime": 9.840012,
    "startPosition": 8.574226994214499,
    "endPosition": 40.82092966298657,
    "velocity": 5.025960402412844,
    "duration": 6.416028,
    "markerSetAt": "2025-10-20T13:28:42.386Z"
  },
  "rampDown": {
    "startIndex": 1703,
    "endIndex": 2610,
    "startTime": 13.632189,
    "endTime": 20.887945,
    "startPosition": 40.6995638061265,
    "endPosition": 8.744143243058963,
    "velocity": 4.404147626114707,
    "duration": 7.255755999999998,
    "markerSetAt": "2025-10-20T13:28:42.386Z"
  },
  "voltageAssignment": 2,
  "voltageAssignedAt": "2025-10-20T13:28:42.386Z",
  "isApproved": true,
  "approvedAt": "2025-10-20T13:28:42.386Z",
  "isManuallyAdjusted": false,
  "manualAdjustmentAt": null,
  "analysisQuality": {
    "detectionConfidence": "high",
    "requiresReview": false,
    "markerDistance": {
      "rampUp": 802,
      "rampDown": 907
    }
  },
  "completeAnalysisData": {
    "fileName": "32405,,SpeedCheck 25-08-06,00001,00000,,00004,S,,920-Strom-Kalibrierung(920).csv",
    "rampUp": {
      "startIndex": 427,
      "endIndex": 1229,
      "startTime": 3.423984,
      "endTime": 9.840012,
      "startPosition": 8.574226994214499,
      "endPosition": 40.82092966298657,
      "velocity": 5.025960402412844,
      "duration": 6.416028
    },
    "rampDown": {
      "startIndex": 1703,
      "endIndex": 2610,
      "startTime": 13.632189,
      "endTime": 20.887945,
      "startPosition": 40.6995638061265,
      "endPosition": 8.744143243058963,
      "velocity": 4.404147626114707,
      "duration": 7.255755999999998
    },
    "detectionMethod": "automatic",
    "createdAt": 1758003600000,
    "createdDate": "2025-09-16T06:20:00.000Z"
  }
}