{
  "fileName": "32405,,SpeedCheck 25-08-06,00001,00000,,00018,S,,920-Strom-Kalibrierung(920).csv",
  "analysisTimestamp": "2025-10-20T13:31:16.179Z",
  "detectionMethod": "automatic",
  "detectionTimestamp": "2025-10-20T13:31:16.179Z",
  "rampUp": {
    "startIndex": 5390,
    "endIndex": 24474,
    "startTime": 43.126335,
    "endTime": 195.785431,
    "startPosition": 5.472529120312442,
    "endPosition": 25.14309093828302,
    "velocity": 0.12885286454185857,
    "duration": 152.65909599999998,
    "markerSetAt": "2025-10-20T13:31:16.179Z"
  },
  "rampDown": {
    "startIndex": 33698,
    "endIndex": 47107,
    "startTime": 269.536896,
    "endTime": 376.749969,
    "startPosition": 25.388970936387466,
    "endPosition": 5.325005170690138,
    "velocity": 0.18714103797488696,
    "duration": 107.21307300000001,
    "markerSetAt": "2025-10-20T13:31:16.179Z"
  },
  "voltageAssignment": 0.1,
  "voltageAssignedAt": "2025-10-20T13:31:16.179Z",
  "isApproved": true,
  "approvedAt": "2025-10-20T13:31:16.179Z",
  "isManuallyAdjusted": false,
  "manualAdjustmentAt": null,
  "analysisQuality": {
    "detectionConfidence": "high",
    "requiresReview": false,
    "markerDistance": {
      "rampUp": 19084,
      "rampDown": 13409
    }
  },
  "completeAnalysisData": {
    "fileName": "32405,,SpeedCheck 25-08-06,00001,00000,,00018,S,,920-Strom-Kalibrierung(920).csv",
    "rampUp": {
      "startIndex": 5390,
      "endIndex": 24474,
      "startTime": 43.126335,
      "endTime": 195.785431,
      "startPosition": 5.472529120312442,
      "endPosition": 25.14309093828302,
      "velocity": 0.12885286454185857,
      "duration": 152.65909599999998
    },
    "rampDown": {
      "startIndex": 33698,
      "endIndex": 47107,
      "startTime": 269.536896,
      "endTime": 376.749969,
      "startPosition": 25.388970936387466,
      "endPosition": 5.325005170690138,
      "velocity": 0.18714103797488696,
      "duration": 107.21307300000001
    },
    "detectionMethod": "automatic",
    "createdAt": 1758003600000,
    "createdDate": "2025-09-16T06:20:00.000Z"
  }
}